docs/Makefile
docs/README.md
docs/callbacks.rst
docs/conf.py
docs/fine_tuning.rst
docs/index.rst
docs/installation.rst
docs/make.bat
docs/quickstart.rst
docs/requirements_docs.txt
docs/run_config.rst
docs/schedulers.rst
docs/tracking.rst
docs/trainer.rst
docs/utils.rst
examples/README.md
examples/__init__.py
examples/core/custom_callback_event.py
examples/core/train_mnist.py
examples/core/train_with_metrics_in_callback.py
examples/core/train_with_metrics_in_loop.py
examples/core/.devcontainer/Dockerfile
examples/core/.devcontainer/devcontainer.json
examples/data/download_ants_and_bees.sh
examples/data/download_imagenette.sh
examples/data/download_pets.sh
examples/nlp/hf_bert_glue_mrpc.py
examples/nlp/.devcontainer/Dockerfile
examples/nlp/.devcontainer/devcontainer.json
examples/vision/__init__.py
examples/vision/faster_rcnn/__init__.py
examples/vision/faster_rcnn/train_cars.py
examples/vision/faster_rcnn/.devcontainer/Dockerfile
examples/vision/faster_rcnn/.devcontainer/devcontainer.json
examples/vision/faster_rcnn/evaluation/calculate_map_callback.py
examples/vision/faster_rcnn/evaluation/coco_evaluator.py
examples/vision/faster_rcnn/frcnn/dataset.py
examples/vision/faster_rcnn/frcnn/model.py
examples/vision/faster_rcnn/frcnn/trainer.py
examples/vision/transfer_learning/__init__.py
examples/vision/transfer_learning/pets_finetune.py
examples/vision/transfer_learning/progressive_resizing.py
examples/vision/transfer_learning/pytorch_tutorial_finetune.py
examples/vision/transfer_learning/.devcontainer/Dockerfile
examples/vision/transfer_learning/.devcontainer/devcontainer.json
examples/vision/using_timm_components/__init__.py
examples/vision/using_timm_components/all_timm_components.py
examples/vision/using_timm_components/train_mixup_ema.py
examples/vision/using_timm_components/.devcontainer/Dockerfile
examples/vision/using_timm_components/.devcontainer/devcontainer.json
pytorch_accelerated/__init__.py
pytorch_accelerated/_version.py
pytorch_accelerated/callbacks.py
pytorch_accelerated-0.1.60.dist-info/licenses/LICENSE.txt
pytorch_accelerated-0.1.60.dist-info/METADATA
pytorch_accelerated-0.1.60.dist-info/WHEEL
pytorch_accelerated-0.1.60.dist-info/top_level.txt
pytorch_accelerated-0.1.60.dist-info/RECORD
