Metadata-Version: 2.4
Name: pytorch-accelerated
Version: 0.1.60
Summary: A lightweight library designed to accelerate the process of training PyTorch models by providing a minimal, but extensible training loop which is flexible enough to handle the majority of use cases, and capable of utilizing different hardware options with no code changes required.
Author-email: Chris Hughes <31883449+Chris-hughes10@users.noreply.github.com>
License: Apache Software License
Project-URL: Homepage, https://github.com/Chris-hughes10/pytorch-accelerated
Project-URL: Repository, https://github.com/Chris-hughes10/pytorch-accelerated
Project-URL: Issues, https://github.com/Chris-hughes10/pytorch-accelerated/issues
Classifier: License :: OSI Approved :: Apache Software License
Classifier: Programming Language :: Python
Classifier: Programming Language :: Python :: 3
Classifier: Programming Language :: Python :: 3.8
Classifier: Programming Language :: Python :: 3.9
Classifier: Programming Language :: Python :: 3.10
Classifier: Programming Language :: Python :: 3.11
Classifier: Programming Language :: Python :: 3.12
Classifier: Programming Language :: Python :: Implementation :: CPython
Requires-Python: >=3.8
License-File: LICENSE.txt
Requires-Dist: accelerate>=1.3.0
Provides-Extra: examples
Requires-Dist: torchvision~=0.18.0; extra == "examples"
Requires-Dist: torchmetrics~=1.3.0; extra == "examples"
Requires-Dist: timm~=0.9.0; extra == "examples"
Requires-Dist: datasets~=2.19.0; extra == "examples"
Dynamic: license-file
